rtx/__init__.py
rtx/__main__.py
rtx/advisory.py
rtx/api.py
rtx/cli.py
rtx/config.py
rtx/exceptions.py
rtx/metadata.py
rtx/models.py
rtx/policy.py
rtx/registry.py
rtx/reporting.py
rtx/sbom.py
rtx/sbom_cli.py
rtx/utils.py
rtx/data/compromised_maintainers.json
rtx/data/report.html.j2
rtx/data/top_packages.json
rtx/scanners/__init__.py
rtx/scanners/base.py
rtx/scanners/brew.py
rtx/scanners/cargo.py
rtx/scanners/common.py
rtx/scanners/composer.py
rtx/scanners/conda.py
rtx/scanners/docker.py
rtx/scanners/go.py
rtx/scanners/maven.py
rtx/scanners/npm.py
rtx/scanners/nuget.py
rtx/scanners/pypi.py
rtx/scanners/rubygems.py
rtx_trust-0.1.0.dist-info/METADATA
rtx_trust-0.1.0.dist-info/WHEEL
rtx_trust-0.1.0.dist-info/entry_points.txt
rtx_trust-0.1.0.dist-info/licenses/LICENSE
rtx_trust-0.1.0.dist-info/RECORD
