Metadata-Version: 2.3
Name: rtx-trust
Version: 0.1.0
Summary: Real Tracker X: cross-ecosystem dependency trust scanner
Project-URL: Homepage, https://github.com/afadesigns/rtx
Project-URL: Documentation, https://afadesigns.github.io/rtx
Project-URL: Repository, https://github.com/afadesigns/rtx
Project-URL: Issues, https://github.com/afadesigns/rtx/issues
Project-URL: Changelog, https://github.com/afadesigns/rtx/blob/main/CHANGELOG.md
Author: Andreas Fahl
License: MIT License
License-File: LICENSE
Keywords: dependencies,osv,sbom,security,supply-chain
Classifier: Development Status :: 4 - Beta
Classifier: Intended Audience :: Developers
Classifier: Intended Audience :: System Administrators
Classifier: License :: OSI Approved :: MIT License
Classifier: Programming Language :: Python :: 3
Classifier: Programming Language :: Python :: 3.11
Classifier: Topic :: Security
Classifier: Topic :: Software Development :: Build Tools
Requires-Python: >=3.11
Requires-Dist: httpx==0.27.0
Requires-Dist: jinja2==3.1.4
Requires-Dist: packaging==24.1
Requires-Dist: pyyaml==6.0.1
Requires-Dist: rich==13.7.1
Provides-Extra: dev
Requires-Dist: bandit==1.7.9; extra == 'dev'
Requires-Dist: coverage==7.6.4; extra == 'dev'
Requires-Dist: hypothesis==6.112.2; extra == 'dev'
Requires-Dist: mypy==1.11.1; extra == 'dev'
Requires-Dist: pytest-asyncio==0.23.7; extra == 'dev'
Requires-Dist: pytest-cov==5.0.0; extra == 'dev'
Requires-Dist: pytest==8.3.3; extra == 'dev'
Requires-Dist: respx==0.20.2; extra == 'dev'
Requires-Dist: ruff==0.6.2; extra == 'dev'
Requires-Dist: semgrep==1.71.0; extra == 'dev'
Requires-Dist: types-pyyaml==6.0.12.20240917; extra == 'dev'
Provides-Extra: docs
Requires-Dist: mkdocs-material==9.5.14; extra == 'docs'
Requires-Dist: mkdocs==1.5.3; extra == 'docs'
Requires-Dist: mkdocstrings[python]==0.25.1; extra == 'docs'
Provides-Extra: fuzz
Requires-Dist: atheris==2.3.0; extra == 'fuzz'
